conductor/__init__.py
conductor/_base_client.py
conductor/_client.py
conductor/_compat.py
conductor/_constants.py
conductor/_exceptions.py
conductor/_files.py
conductor/_models.py
conductor/_qs.py
conductor/_resource.py
conductor/_response.py
conductor/_streaming.py
conductor/_types.py
conductor/_version.py
conductor/pagination.py
conductor/py.typed
conductor/_utils/__init__.py
conductor/_utils/_compat.py
conductor/_utils/_datetime_parse.py
conductor/_utils/_logs.py
conductor/_utils/_proxy.py
conductor/_utils/_reflection.py
conductor/_utils/_resources_proxy.py
conductor/_utils/_streams.py
conductor/_utils/_sync.py
conductor/_utils/_transform.py
conductor/_utils/_typing.py
conductor/_utils/_utils.py
conductor/lib/.keep
conductor/resources/__init__.py
conductor/resources/auth_sessions.py
conductor/resources/end_users.py
conductor/resources/qbd/__init__.py
conductor/resources/qbd/account_tax_lines.py
conductor/resources/qbd/accounts.py
conductor/resources/qbd/bill_check_payments.py
conductor/resources/qbd/bill_credit_card_payments.py
conductor/resources/qbd/bills.py
conductor/resources/qbd/build_assemblies.py
conductor/resources/qbd/checks.py
conductor/resources/qbd/classes.py
conductor/resources/qbd/company.py
conductor/resources/qbd/credit_card_charges.py
conductor/resources/qbd/credit_card_credits.py
conductor/resources/qbd/credit_card_refunds.py
conductor/resources/qbd/credit_memos.py
conductor/resources/qbd/currencies.py
conductor/resources/qbd/customer_types.py
conductor/resources/qbd/customers.py
conductor/resources/qbd/date_driven_terms.py
conductor/resources/qbd/deleted_list_objects.py
conductor/resources/qbd/deleted_transactions.py
conductor/resources/qbd/discount_items.py
conductor/resources/qbd/employees.py
conductor/resources/qbd/estimates.py
conductor/resources/qbd/inventory_adjustments.py
conductor/resources/qbd/inventory_assembly_items.py
conductor/resources/qbd/inventory_items.py
conductor/resources/qbd/inventory_sites.py
conductor_py-1.69.0.dist-info/METADATA
conductor_py-1.69.0.dist-info/WHEEL
conductor_py-1.69.0.dist-info/licenses/LICENSE
conductor_py-1.69.0.dist-info/RECORD
